hyperflow_py_models/__init__.py
hyperflow_py_models/db/base.py
hyperflow_py_models/db/enriched_trade.py
hyperflow_py_models/db/models/base.py
hyperflow_py_models/db/models/enriched_trade.py
hyperflow_py_models/db/models/position.py
hyperflow_py_models/db/models/raw_trade.py
hyperflow_py_models/db/models/trade_base.py
hyperflow_py_models/db/position.py
hyperflow_py_models/db/raw_trade.py
hyperflow_py_models/db/repository/crud.py
hyperflow_py_models/db/trade_base.py
hyperflow_py_models/hyperflow/core/v1/__init__.py
hyperflow_py_models/hyperflow/core/v1/models.py
hyperflow_py_models/hyperflow/core/v1/models_grpc.py
hyperflow_py_models/schemas/__init__.py
hyperflow_py_models/schemas/api_wrappers.py
hyperflow_py_models/schemas/custom_configs.py
hyperflow_py_models/utils/string.py
hyperflow_py_models-0.1.9.dist-info/METADATA
hyperflow_py_models-0.1.9.dist-info/WHEEL
hyperflow_py_models-0.1.9.dist-info/RECORD
